examples/__init__.py
examples/add_remove_idea.py
examples/attach_file_idea.py
examples/manage_members.py
examples/vote_comment_idea.py
ideascaly/__init__.py
ideascaly/api.py
ideascaly/auth.py
ideascaly/binder.py
ideascaly/error.py
ideascaly/models.py
ideascaly/parsers.py
ideascaly/utils.py
ideascaly-1.0.dist-info/DESCRIPTION.rst
ideascaly-1.0.dist-info/METADATA
ideascaly-1.0.dist-info/metadata.json
ideascaly-1.0.dist-info/RECORD
ideascaly-1.0.dist-info/top_level.txt
ideascaly-1.0.dist-info/WHEEL
ideascaly-1.0.dist-info/zip-safe
