Metadata-Version: 2.0
Name: ideascaly
Version: 1.0
Summary: IdeaScale RESTful API Client
Home-page: https://github.com/joausaga/ideascaly
Author: Jorge Saldivar
Author-email: me@jorgesaldivargalli.com
License: MIT
Keywords: ideascale api client
Platform: UNKNOWN
Classifier: Development Status :: 3 - Alpha
Classifier: Intended Audience :: Developers
Classifier: Topic :: Software Development :: Libraries
Classifier: License :: OSI Approved :: MIT License
Classifier: Operating System :: OS Independent
Classifier: Programming Language :: Python
Classifier: Programming Language :: Python :: 2
Classifier: Programming Language :: Python :: 2.6
Classifier: Programming Language :: Python :: 2.7
Classifier: Programming Language :: Python :: 3
Classifier: Programming Language :: Python :: 3.3
Classifier: Programming Language :: Python :: 3.4
Requires-Dist: configparser (==3.5.0b2)
Requires-Dist: python-dateutil (==2.4.2)
Requires-Dist: requests (==2.6.0)
Requires-Dist: six (==1.9.0)
